back_cleaner/__init__.py
back_cleaner/cleaner.py
back_cleaner-0.0.2.dist-info/LICENSE.txt
back_cleaner-0.0.2.dist-info/METADATA
back_cleaner-0.0.2.dist-info/WHEEL
back_cleaner-0.0.2.dist-info/top_level.txt
back_cleaner-0.0.2.dist-info/RECORD
