Metadata-Version: 2.1
Name: back-cleaner
Version: 0.0.2
Summary: Server-side Python tool for escaping script tags and converting characters into HTML entity equivalents (no regex)
Home-page: https://github.com/Rairye/back-cleaner
Author: Rairye
License: apache-2.0
Download-URL: https://github.com/Rairye/back-cleaner/archive/refs/tags/v0.0.2.tar.gz
Keywords: HTML,entities,script,escape,serverside
Platform: UNKNOWN
Classifier: Development Status :: 3 - Alpha
Classifier: Intended Audience :: End Users/Desktop
Classifier: Intended Audience :: Developers
Classifier: License :: OSI Approved :: Apache Software License
Classifier: Programming Language :: Python :: 3
Classifier: Programming Language :: Python :: 3.1
Classifier: Programming Language :: Python :: 3.2
Classifier: Programming Language :: Python :: 3.3
Classifier: Programming Language :: Python :: 3.4
Classifier: Programming Language :: Python :: 3.5
Classifier: Programming Language :: Python :: 3.6
Classifier: Programming Language :: Python :: 3.7
License-File: LICENSE.txt
